gh_actions_package_onetwothree/__init__.py
gh_actions_package_onetwothree/example.py
gh_actions_package_onetwothree-0.0.1.dist-info/METADATA
gh_actions_package_onetwothree-0.0.1.dist-info/WHEEL
gh_actions_package_onetwothree-0.0.1.dist-info/licenses/LICENSE
gh_actions_package_onetwothree-0.0.1.dist-info/RECORD
